{
  "_id": "home",
  "label": "Home",
  "picture": "public/assets/profile_picture.jpg",
  "resume": "public/assets/Sumedha_Minocha_Resume.pdf",
  "title": "Sumedha Minocha",
  "email": "sm2776@cornell.edu",
  "phone": "+91 9988776655",
  "description": "I am a Ph.D. candidate at Cornell University, Charles H. Dyson School of Applied Economics (Area of Concentration: International & Development Economics).",
  "research_interests": [
    "Social Protection Programs",
    "Gender",
    "Nutrition",
    "Health",
    "Agriculture"
  ]
}